[
    {
        "name": "id",
        "dbType": "integer,false",
        "htmlType": "number",
        "validations": "",
        "searchable": true,
        "fillable": true,
        "primary": false,
        "inForm": true,
        "inIndex": true,
        "inView": true
    },
    {
        "name": "certificate_id",
        "dbType": "string",
        "htmlType": "text",
        "validations": "required|string|max:50|string|max:50|string|max:50",
        "searchable": true,
        "fillable": true,
        "primary": false,
        "inForm": true,
        "inIndex": true,
        "inView": true
    },
    {
        "name": "recipient_name",
        "dbType": "string",
        "htmlType": "text",
        "validations": "required|string|max:255|string|max:255|string|max:255",
        "searchable": true,
        "fillable": true,
        "primary": false,
        "inForm": true,
        "inIndex": true,
        "inView": true
    },
    {
        "name": "recipient_email",
        "dbType": "string",
        "htmlType": "text",
        "validations": "required|string|max:255|string|max:255|string|max:255",
        "searchable": true,
        "fillable": true,
        "primary": false,
        "inForm": true,
        "inIndex": true,
        "inView": true
    },
    {
        "name": "course_name",
        "dbType": "text",
        "htmlType": "textarea",
        "validations": "required|string|max:65535|string|max:65535|string|max:65535",
        "searchable": true,
        "fillable": true,
        "primary": false,
        "inForm": true,
        "inIndex": true,
        "inView": true
    },
    {
        "name": "course_description",
        "dbType": "text",
        "htmlType": "textarea",
        "validations": "nullable|string|max:65535|nullable|string|max:65535|nullable|string|max:65535",
        "searchable": true,
        "fillable": true,
        "primary": false,
        "inForm": true,
        "inIndex": true,
        "inView": true
    },
    {
        "name": "issue_date",
        "dbType": "date",
        "htmlType": "date",
        "validations": "nullable|nullable|nullable",
        "searchable": true,
        "fillable": true,
        "primary": false,
        "inForm": true,
        "inIndex": true,
        "inView": true
    },
    {
        "name": "status",
        "dbType": "string",
        "htmlType": "text",
        "validations": "nullable|string|max:50|nullable|string|max:50|nullable|string|max:50",
        "searchable": true,
        "fillable": true,
        "primary": false,
        "inForm": true,
        "inIndex": true,
        "inView": true
    },
    {
        "name": "email_sent_at",
        "dbType": "datetime",
        "htmlType": "date",
        "validations": "nullable|nullable|nullable",
        "searchable": true,
        "fillable": true,
        "primary": false,
        "inForm": true,
        "inIndex": true,
        "inView": true
    },
    {
        "name": "created_at",
        "dbType": "datetime",
        "htmlType": "date",
        "validations": "nullable|nullable|nullable",
        "searchable": false,
        "fillable": false,
        "primary": false,
        "inForm": false,
        "inIndex": false,
        "inView": false
    },
    {
        "name": "updated_at",
        "dbType": "datetime",
        "htmlType": "date",
        "validations": "nullable|nullable|nullable",
        "searchable": false,
        "fillable": false,
        "primary": false,
        "inForm": false,
        "inIndex": false,
        "inView": false
    }
]