[
    {
        "name": "id",
        "dbType": "integer,false",
        "htmlType": "number",
        "validations": "",
        "searchable": true,
        "fillable": true,
        "primary": false,
        "inForm": true,
        "inIndex": true,
        "inView": true
    },
    {
        "name": "license_type",
        "dbType": "string",
        "htmlType": "text",
        "validations": "",
        "searchable": true,
        "fillable": true,
        "primary": false,
        "inForm": true,
        "inIndex": true,
        "inView": true
    },
    {
        "name": "class",
        "dbType": "string",
        "htmlType": "text",
        "validations": "",
        "searchable": true,
        "fillable": true,
        "primary": false,
        "inForm": true,
        "inIndex": true,
        "inView": true
    },
    {
        "name": "scope",
        "dbType": "text",
        "htmlType": "textarea",
        "validations": "",
        "searchable": true,
        "fillable": true,
        "primary": false,
        "inForm": true,
        "inIndex": true,
        "inView": true
    },
    {
        "name": "min_qualification",
        "dbType": "string",
        "htmlType": "text",
        "validations": "",
        "searchable": true,
        "fillable": true,
        "primary": false,
        "inForm": true,
        "inIndex": true,
        "inView": true
    },
    {
        "name": "technical_qualification",
        "dbType": "text",
        "htmlType": "textarea",
        "validations": "",
        "searchable": true,
        "fillable": true,
        "primary": false,
        "inForm": true,
        "inIndex": true,
        "inView": true
    },
    {
        "name": "experience_requirements",
        "dbType": "text",
        "htmlType": "textarea",
        "validations": "",
        "searchable": true,
        "fillable": true,
        "primary": false,
        "inForm": true,
        "inIndex": true,
        "inView": true
    },
    {
        "name": "starting_license",
        "dbType": "string",
        "htmlType": "text",
        "validations": "",
        "searchable": true,
        "fillable": true,
        "primary": false,
        "inForm": true,
        "inIndex": true,
        "inView": true
    },
    {
        "name": "highest_achievable",
        "dbType": "string",
        "htmlType": "text",
        "validations": "",
        "searchable": true,
        "fillable": true,
        "primary": false,
        "inForm": true,
        "inIndex": true,
        "inView": true
    },
    {
        "name": "created_at",
        "dbType": "datetime",
        "htmlType": "date",
        "validations": "",
        "searchable": false,
        "fillable": false,
        "primary": false,
        "inForm": false,
        "inIndex": false,
        "inView": false
    },
    {
        "name": "updated_at",
        "dbType": "datetime",
        "htmlType": "date",
        "validations": "",
        "searchable": false,
        "fillable": false,
        "primary": false,
        "inForm": false,
        "inIndex": false,
        "inView": false
    }
]